volgactf.final.checker.result-1.0.0-py2.7-nspkg.pth
volgactf/final/checker/result/__about__.py
volgactf/final/checker/result/__init__.py
volgactf.final.checker.result-1.0.0.dist-info/METADATA
volgactf.final.checker.result-1.0.0.dist-info/RECORD
volgactf.final.checker.result-1.0.0.dist-info/WHEEL
volgactf.final.checker.result-1.0.0.dist-info/namespace_packages.txt
volgactf.final.checker.result-1.0.0.dist-info/top_level.txt
