Metadata-Version: 2.1
Name: volgactf.final.checker.result
Version: 1.0.0
Summary: VolgaCTF Final checker result constants
Home-page: https://github.com/VolgaCTF/volgactf-final-checker-result-py
Author: Alexander Pyatkin
Author-email: aspyatkin@gmail.com
License: MIT
Platform: UNKNOWN
Requires-Dist: setuptools (>=35.0.0)
Requires-Dist: enum34 (>=1.1.6); python_version<"3.4"
